ansys/tools/report/__init__.py
ansys/tools/report/_version.py
ansys/tools/report/report.py
pyansys_tools_report-0.8.3.dist-info/licenses/LICENSE
pyansys_tools_report-0.8.3.dist-info/WHEEL
pyansys_tools_report-0.8.3.dist-info/METADATA
pyansys_tools_report-0.8.3.dist-info/RECORD
