Metadata-Version: 2.4
Name: pyansys-tools-report
Version: 0.8.3
Summary: PyAnsys Tools Report package.
Author-email: "ANSYS, Inc." <pyansys.core@ansys.com>
Maintainer-email: "ANSYS, Inc." <pyansys.core@ansys.com>
Requires-Python: >=3.10,<4
Classifier: Development Status :: 4 - Beta
Classifier: Programming Language :: Python :: 3.10
Classifier: Programming Language :: Python :: 3.11
Classifier: Programming Language :: Python :: 3.12
Classifier: Programming Language :: Python :: 3.13
Classifier: License :: OSI Approved :: MIT License
Classifier: Operating System :: OS Independent
License-File: LICENSE
Requires-Dist: setuptools>=65.5.1
Requires-Dist: scooby>=0.5.12
Requires-Dist: ansys_sphinx_theme==1.6.0 ; extra == "doc"
Requires-Dist: myst-parser==4.0.1 ; extra == "doc"
Requires-Dist: numpydoc==1.9.0 ; extra == "doc"
Requires-Dist: scooby==0.10.1 ; extra == "doc"
Requires-Dist: Sphinx==8.2.3 ; extra == "doc"
Requires-Dist: Sphinx-copybutton==0.5.2 ; extra == "doc"
Requires-Dist: pytest==8.4.2 ; extra == "tests"
Requires-Dist: pytest-cov==6.3.0 ; extra == "tests"
Requires-Dist: scooby==0.10.1 ; extra == "tests"
Project-URL: Source, https://github.com/ansys/pyansys-tools-report
Provides-Extra: doc
Provides-Extra: tests
